optrade/__init__.py
optrade/analysis/__init__.py
optrade/analysis/factors.py
optrade/analysis/plotting.py
optrade/analysis/visualizer.py
optrade/assets/optrade_dark.png
optrade/assets/optrade_light.png
optrade/config/__init__.py
optrade/config/config.py
optrade/data/__init__.py
optrade/data/contracts.py
optrade/data/features.py
optrade/data/forecasting.py
optrade/data/thetadata.py
optrade/data/universe.py
optrade/dev/download_universe.py
optrade/dev/grid_search.py
optrade/dev/run.py
optrade/dev/utils/ablations.py
optrade/dev/utils/logger.py
optrade/dev/utils/models.py
optrade/dev/utils/schedulers.py
optrade/exp/__init__.py
optrade/exp/evaluate.py
optrade/exp/forecasting.py
optrade/jobs/parent/test/ablation.yaml
optrade/jobs/parent/test/market_metrics.json
optrade/jobs/parent/test/universe.yaml
optrade/jobs/parent/v0/ablation.yaml
optrade/jobs/parent/v0/universe.yaml
optrade/jobs/parent/v1/ablation.yaml
optrade/jobs/parent/v1/universe.yaml
optrade/jobs/scripts/v1/run.sh
optrade/jobs/v0/ridge/ablation.yaml
optrade/jobs/v0/ridge/args.yaml
optrade/jobs/v1/emforecaster/ablation.yaml
optrade/jobs/v1/emforecaster/args.yaml
optrade/main.py
optrade/models/__init__.py
optrade/models/classical/__init__.py
optrade/models/classical/_sklearn.py
optrade/models/classical/_sktime.py
optrade/models/pytorch/__init__.py
optrade/models/pytorch/dlinear.py
optrade/models/pytorch/emforecaster.py
optrade/models/pytorch/linear.py
optrade/models/pytorch/mamba.py
optrade/models/pytorch/patchtst.py
optrade/models/pytorch/recurrent.py
optrade/models/pytorch/tsmixer.py
optrade/models/utils/__init__.py
optrade/models/utils/patcher.py
optrade/models/utils/pos_enc.py
optrade/models/utils/revin.py
optrade/models/utils/utils.py
optrade/models/utils/weight_init.py
optrade/utils/__init__.py
optrade/utils/directories.py
optrade/utils/error_handlers.py
optrade/utils/misc.py
optrade/utils/stock_categories.py
optrade/utils/train.py
optrade/utils/volatility.py
optrade-1.0.0.dist-info/LICENSE
optrade-1.0.0.dist-info/METADATA
optrade-1.0.0.dist-info/WHEEL
optrade-1.0.0.dist-info/RECORD
