Metadata-Version: 2.3
Name: optrade
Version: 1.0.0
Summary: Options Forecasting and Trading Framework for Quantitative Research
License: MIT
Author: Xavier Mootoo
Requires-Python: >=3.9,<3.14
Classifier: License :: OSI Approved :: MIT License
Classifier: Programming Language :: Python :: 3
Classifier: Programming Language :: Python :: 3.9
Classifier: Programming Language :: Python :: 3.10
Classifier: Programming Language :: Python :: 3.11
Classifier: Programming Language :: Python :: 3.12
Classifier: Programming Language :: Python :: 3.13
Requires-Dist: catboost (>=1.2.8,<2.0.0)
Requires-Dist: httpx (>=0.28.1,<0.29.0)
Requires-Dist: mambapy (>=1.2.0,<2.0.0)
Requires-Dist: matplotlib (>=3.7.0,<4.0.0)
Requires-Dist: neptune (>=1.14.0,<2.0.0)
Requires-Dist: numpy (>=1.24.0,<3.0.0)
Requires-Dist: pandas (>=2.1.0,<3.0.0)
Requires-Dist: pandas-datareader (>=0.10.0,<0.11.0)
Requires-Dist: pandas-market-calendars (>=5.1.0,<6.0.0)
Requires-Dist: py-vollib (>=1.0.1,<2.0.0)
Requires-Dist: pydantic (>=2.11.4,<3.0.0)
Requires-Dist: pyyaml (>=6.0.2,<7.0.0)
Requires-Dist: rich (>=14.0.0,<15.0.0)
Requires-Dist: scikit-learn (>=1.6.1,<2.0.0)
Requires-Dist: sktime (>=0.37.0,<0.38.0)
Requires-Dist: statsmodels (>=0.14.4,<0.15.0)
Requires-Dist: torch (>=2.7.0,<3.0.0)
Requires-Dist: xgboost (>=2.0.0)
Requires-Dist: yfinance (>=0.2.58,<0.3.0)
